pyodourcollect/__init__.py
pyodourcollect/__main__.py
pyodourcollect/command_line.py
pyodourcollect/constants.py
pyodourcollect/core.py
pyodourcollect/helpers.py
pyodourcollect/main.py
pyodourcollect/models.py
pyodourcollect/occore.py
pyodourcollect/ochelpers.py
pyodourcollect/ocmodels.py
pyodourcollect-1.0.0.dist-info/LICENSE
pyodourcollect-1.0.0.dist-info/METADATA
pyodourcollect-1.0.0.dist-info/WHEEL
pyodourcollect-1.0.0.dist-info/entry_points.txt
pyodourcollect-1.0.0.dist-info/top_level.txt
pyodourcollect-1.0.0.dist-info/RECORD
