Metadata-Version: 2.1
Name: pyodourcollect
Version: 1.0.0
Summary: Get real time odour observations from OdourCollect's Citizen Observatory
Home-page: https://github.com/ScienceForChange/PyOdourCollect
Author: Alex Amo (OdourCollect) and Ana Álvarez (COS4CLOUD)
Author-email: alex.amo@scienceforchange.eu
License: GPLv3
Platform: UNKNOWN
Classifier: License :: OSI Approved :: GNU General Public License v3 (GPLv3)
Classifier: Programming Language :: Python :: 3
Classifier: Programming Language :: Python :: 3.7
Classifier: Development Status :: 4 - Beta
License-File: LICENSE
Requires-Dist: requests
Requires-Dist: pydantic
Requires-Dist: haversine
Requires-Dist: openpyxl
Requires-Dist: pandas
